setup.py
chainmail/__init__.py
chainmail/chainmail.py
chainmail.egg-info/PKG-INFO
chainmail.egg-info/SOURCES.txt
chainmail.egg-info/dependency_links.txt
chainmail.egg-info/requires.txt
chainmail.egg-info/top_level.txt