Metadata-Version: 1.1
Name: chainmail
Version: 0.1.2
Summary: Sending email is hard. Let's go shopping!
Home-page: http://github.com/duckworthd/chainmail
Author: Daniel Duckworth
Author-email: duckworthd@gmail.com
License: BSD
Keywords: smtp email
Platform: UNKNOWN
Classifier: Development Status :: 4 - Beta
Classifier: License :: OSI Approved :: BSD License
Classifier: Operating System :: OS Independent
Classifier: Programming Language :: Python
